fandango/__init__.py
fandango/abstract_bucket.py
fandango/abstract_field.py
fandango/abstract_record.py
fandango/api_client.py
fandango/aria_client.py
fandango/bucket.py
fandango/cli_data_manager.py
fandango/client_data_manager.py
fandango/client_entity_manager.py
fandango/client_oauth.py
fandango/data_manager.py
fandango/entity_manager.py
fandango/field.py
fandango/imports_config.py
fandango/oauth.py
fandango/record.py
fandango/token.py
fandango/utils.py
fandango/visit.py
fandango/commands/__init__.py
fandango/commands/cli.py
fandango/commands/create_bucket.py
fandango/commands/create_field.py
fandango/commands/create_record.py
fandango/commands/get_visits.py
fandango/commands/help.py
fandango/commands/list_buckets.py
fandango/commands/list_fields.py
fandango/commands/list_records.py
fandango/commands/login.py
fandango/config/__init__.py
fandango/config/config.yml
fandango_aria_plugin-1.0.3.dist-info/LICENSE.txt
fandango_aria_plugin-1.0.3.dist-info/METADATA
fandango_aria_plugin-1.0.3.dist-info/WHEEL
fandango_aria_plugin-1.0.3.dist-info/entry_points.txt
fandango_aria_plugin-1.0.3.dist-info/top_level.txt
fandango_aria_plugin-1.0.3.dist-info/RECORD
