Metadata-Version: 2.1
Name: fandango-aria-plugin
Version: 1.0.3
Summary: A Public Client library and CLI for interacting with ARIA's Data Deposition Service.
Home-page: https://github.com/FragmentScreen/fandango-aria-plugin
Author: Lui Holliday, Instruct-ERIC
Author-email: lui.holliday@instruct-eric.org
License: MIT
License-File: LICENSE.txt
Requires-Dist: click
Requires-Dist: requests
Requires-Dist: keyring
Requires-Dist: questionary
Requires-Dist: PyYAML
